provider/__init__.py
provider/access.py
provider/cli/__init__.py
provider/cli/main.py
provider/config/__init__.py
provider/config/loaders.py
provider/config/tests/test_configurer.py
provider/config/tests/test_loaders.py
provider/dataclass.py
provider/diagnostics.py
provider/health.py
provider/namespace.py
provider/provider.py
provider/resources.py
provider/rpc.py
provider/runtime/__init__.py
provider/runtime/aws_lambda.py
provider/runtime/aws_lambda_entrypoint.py
provider/runtime/initialise.py
provider/runtime/tests/__init__.py
provider/runtime/tests/__snapshots__/aws_lambda_test/test_grant_works.json
provider/runtime/tests/__snapshots__/aws_lambda_test/test_load_works.json
provider/runtime/tests/__snapshots__/aws_lambda_test/test_load_works_with_subtasks.json
provider/runtime/tests/__snapshots__/aws_lambda_test/test_provider_describe.json
provider/runtime/tests/__snapshots__/aws_lambda_test/test_provider_describe_with_config.json
provider/runtime/tests/__snapshots__/aws_lambda_test/test_provider_describe_with_errors.json
provider/runtime/tests/__snapshots__/aws_lambda_test/test_provider_describe_with_resources.json
provider/runtime/tests/aws_lambda_entrypoint_test.py
provider/runtime/tests/aws_lambda_test.py
provider/runtime/tests/commonfate_provider_dist/README.md
provider/runtime/tests/commonfate_provider_dist/__init__.py
provider/runtime/tests/commonfate_provider_dist/manifest.json
provider/runtime/tests/initialise_test.py
provider/runtime/tests/provider_example/__init__.py
provider/runtime/tests/provider_example/provider.py
provider/schema.py
provider/target.py
provider/tasks.py
provider/tests/__init__.py
provider/tests/access_test.py
provider/tests/health_test.py
provider/tests/helper.py
provider/tests/provider_test.py
provider/tests/resources_test.py
provider/tests/schema_test.py
provider/tests/storage_test.py
provider/tests/target_test.py
provider-0.10.0.dist-info/entry_points.txt
provider-0.10.0.dist-info/WHEEL
provider-0.10.0.dist-info/METADATA
provider-0.10.0.dist-info/RECORD
